mindose/__init__.py
mindose/_modidx.py
mindose/core.py
mindose-0.0.1.dist-info/LICENSE
mindose-0.0.1.dist-info/METADATA
mindose-0.0.1.dist-info/WHEEL
mindose-0.0.1.dist-info/entry_points.txt
mindose-0.0.1.dist-info/top_level.txt
mindose-0.0.1.dist-info/RECORD
